pynfc/__init__.py
pynfc/class_conversions.py
pynfc/class_nfc.py
pynfc/class_nfc_old.py
pynfc/class_reference.py
pynfc/nfc_communication.json
yongshi_pynfc-0.4.4.data/data/pynfc/nfc_communication.json
yongshi_pynfc-0.4.4.dist-info/LICENSE
yongshi_pynfc-0.4.4.dist-info/METADATA
yongshi_pynfc-0.4.4.dist-info/WHEEL
yongshi_pynfc-0.4.4.dist-info/top_level.txt
yongshi_pynfc-0.4.4.dist-info/RECORD
