Metadata-Version: 2.1
Name: yongshi-pynfc
Version: 0.4.4
Summary: A library can be used to interact with nfc cards and readers.
Home-page: https://github.com/Michael-Yongshi/Py-Library-NFC
Author: Michael-Yongshi
Author-email: 4registration@outlook.com
License: UNKNOWN
Platform: UNKNOWN
Classifier: Programming Language :: Python :: 3
Classifier: License :: OSI Approved :: GNU General Public License v3 or later (GPLv3+)
Classifier: Operating System :: OS Independent
Requires-Python: >=3.3
